[
  {
    "timestamp": "2025-10-11T15:19:43.293Z",
    "category": "execution",
    "name": "agent_stage_atlas",
    "value": 830,
    "tags": {
      "success": true,
      "stage": 0,
      "name": "stage0_chat",
      "contextSize": 2
    }
  },
  {
    "timestamp": "2025-10-11T15:19:43.296Z",
    "category": "execution",
    "name": "http_request",
    "value": 2374,
    "tags": {
      "success": true,
      "method": "POST",
      "path": "/chat/stream",
      "status": 200
    }
  },
  {
    "timestamp": "2025-10-11T15:19:53.753Z",
    "category": "execution",
    "name": "http_request",
    "value": 2,
    "tags": {
      "success": true,
      "method": "POST",
      "path": "/tts/completed",
      "status": 200
    }
  }
]