[
  {
    "timestamp": "2025-10-10T08:45:53.665Z",
    "category": "resource",
    "name": "cpu",
    "value": 2.1669921875,
    "tags": {}
  },
  {
    "timestamp": "2025-10-10T08:45:53.665Z",
    "category": "resource",
    "name": "memory",
    "value": 0.7909832000732422,
    "tags": {}
  },
  {
    "timestamp": "2025-10-10T08:46:53.665Z",
    "category": "resource",
    "name": "cpu",
    "value": 1.861328125,
    "tags": {}
  },
  {
    "timestamp": "2025-10-10T08:46:53.665Z",
    "category": "resource",
    "name": "memory",
    "value": 0.7935223579406738,
    "tags": {}
  }
]