[
  {
    "timestamp": "2025-10-10T19:20:38.028Z",
    "category": "resource",
    "name": "cpu",
    "value": 4.80126953125,
    "tags": {}
  },
  {
    "timestamp": "2025-10-10T19:20:38.028Z",
    "category": "resource",
    "name": "memory",
    "value": 0.9939584732055664,
    "tags": {}
  },
  {
    "timestamp": "2025-10-10T19:21:38.028Z",
    "category": "resource",
    "name": "cpu",
    "value": 4.6572265625,
    "tags": {}
  },
  {
    "timestamp": "2025-10-10T19:21:38.028Z",
    "category": "resource",
    "name": "memory",
    "value": 0.9938144683837891,
    "tags": {}
  }
]